.travis.yml
AUTHORS.rst
HISTORY.rst
LICENSE.txt
MANIFEST.in
README.rst
build_python_from_src.txt
build_results.txt
install_linux_headers.txt
pyenv_help.txt
pyproject.toml
requirements.txt
setup.cfg
setup.py
setup_ubuntu_f2py.txt
tox.ini
venv_runs.txt
genericf2py/__init__.py
genericf2py/_version.py
genericf2py/find_mingw_lib.py
genericf2py/main.py
genericf2py/nosetests_details.txt
genericf2py.egg-info/PKG-INFO
genericf2py.egg-info/SOURCES.txt
genericf2py.egg-info/dependency_links.txt
genericf2py.egg-info/not-zip-safe
genericf2py.egg-info/requires.txt
genericf2py.egg-info/top_level.txt
genericf2py/src/fprog.f
genericf2py/examples/example_1.py
genericf2py/src/checkout.py
genericf2py/src/fprog.cp38-win_amd64.pyd
genericf2py/src/fprog.f
genericf2py/src/fprog.inc
genericf2py/src/make_win32bit.bat
genericf2py/src/make_win64bit.bat
genericf2py/tests/__init__.py
genericf2py/tests/test_main.py